{
  "build_list": [
    {
      "name": "Core Land Mine - Field",
      "to_build": "CoreT1DefenceMine",
      "instance_count": -1,
      "priority": 261,
      "base_sort": "FromBuilder",
      "builders": ["CoreT1VehicleMine"],
      "build_conditions": [
        [
          {
            "test_type": "EnemySurfacePresenceOnPlanet",
            "boolean": true
          },
          {
            "test_type": "UnitCountInBase",
            "unit_type_string0": "Structure - Factory - CombatFabBuild",
            "compare0": ">=",
            "value0": 1
          },
          {
            "test_type": "UnitCountInBase",
            "unit_type_string0": "Structure & CombatFabBuild & Defense",
            "compare0": ">",
            "value0": 0
          },
          {
            "test_type": "UnitCountInBase",
            "unit_type_string0": "Structure & CombatFabBuild & Defense",
            "compare0": "<",
            "value0": 25
          },
          {
            "test_type": "UnitCountInBase",
            "unit_type_string0": "Structure & (Factory | Teleporter)",
            "compare0": "<",
            "value0": 1
          },
          {
            "test_type": "CanFindPlaceToBuild",
            "string0": "CoreT1VehicleMine"
          }
        ]
      ],
      "placement_rules": {
        "buffer": 2,
        "placement_type": "FromMainBasePerimeter",
        "threat": {
          "influence_type": "AntiSurface",
          "compare_type": "<",
          "radius": 35,
          "value": 5
        }
      }
    },
    {
      "name": "Core Land Mine - Mex",
      "to_build": "CoreT1DefenceMine",
      "instance_count": -1,
      "priority": 260,
      "base_sort": "FromPerimeter",
      "builders": ["CoreT1VehicleMine"],
      "build_conditions": [
        [
          {
            "test_type": "EnemySurfacePresenceOnPlanet",
            "boolean": true
          },
          {
            "test_type": "DistFromMainBase",
            "compare0": ">=",
            "value0": 150
          },
          {
            "test_type": "UnitCountInBase",
            "unit_type_string0": "Structure - Factory - CombatFabBuild",
            "compare0": ">=",
            "value0": 1
          },
          {
            "test_type": "UnitCountInBase",
            "unit_type_string0": "Structure & CombatFabBuild & Defense",
            "compare0": "<",
            "value0": 25
          },
          {
            "test_type": "UnitCountInBase",
            "unit_type_string0": "Structure & (Factory | Teleporter)",
            "compare0": "<",
            "value0": 1
          },
          {
            "test_type": "CanAffordBuildDemand"
          },
          {
            "test_type": "CanFindPlaceToBuild",
            "string0": "CoreT1VehicleMine"
          }
        ],
        [
          {
            "test_type": "EnemySurfacePresenceOnPlanet",
            "boolean": true
          },
          {
            "test_type": "DistFromNearestEnemyThreat",
            "compare0": "<=",
            "value0": 100
          },
          {
            "test_type": "UnitCountInBase",
            "unit_type_string0": "Structure - Factory - CombatFabBuild",
            "compare0": ">=",
            "value0": 1
          },
          {
            "test_type": "UnitCountInBase",
            "unit_type_string0": "Structure & CombatFabBuild & Defense",
            "compare0": "<",
            "value0": 25
          },
          {
            "test_type": "UnitCountInBase",
            "unit_type_string0": "Structure & (Factory | Teleporter)",
            "compare0": "<",
            "value0": 1
          },
          {
            "test_type": "CanAffordBuildDemand"
          },
          {
            "test_type": "CanFindPlaceToBuild",
            "string0": "CoreT1VehicleMine"
          }
        ]
      ],
      "placement_rules": {
        "buffer": 2,
        "placement_type": "FromMainBasePerimeter",
        "threat": {
          "influence_type": "AntiSurface",
          "compare_type": "<",
          "radius": 35,
          "value": 5
        }
      }
    },
    {
      "name": "Core Nuclear Land Mine - Mex",
      "to_build": "CoreT1DefenceMineNuke",
      "instance_count": 1,
      "priority": 0,
      "base_sort": "FromPerimeter",
      "builders": ["CoreT1VehicleMine"],
      "build_conditions": [
        [
          {
            "test_type": "EnemySurfacePresenceOnPlanet",
            "boolean": true
          },
          {
            "test_type": "PlanetThreat",
            "string0": "Economy",
            "compare0": ">",
            "value0": 5000
          },
          {
            "test_type": "DistFromMainBase",
            "compare0": ">=",
            "value0": 150
          },
          {
            "test_type": "UnitCountInBase",
            "unit_type_string0": "Structure - Factory - CombatFabBuild",
            "compare0": ">=",
            "value0": 1
          },
          {
            "test_type": "UnitCountInBase",
            "unit_type_string0": "Structure & CombatFabBuild & Defense",
            "compare0": "<",
            "value0": 1
          },
          {
            "test_type": "UnitCountInBase",
            "unit_type_string0": "Structure & (Factory | Teleporter)",
            "compare0": "<",
            "value0": 1
          },
          {
            "test_type": "CanAffordBuildDemand"
          },
          {
            "test_type": "CanFindPlaceToBuild",
            "string0": "CoreT1DefenceMineNuke"
          }
        ]
      ],
      "placement_rules": {
        "buffer": 2,
        "placement_type": "FromMainBasePerimeter",
        "unit_count_rules": [
          {
            "unit_type_string": "Structure & CombatFabBuild & Defense",
            "alliance": "Ally",
            "compare_type": "<",
            "range": 75,
            "count": 1
          }
        ],
        "threat": {
          "influence_type": "AntiSurface",
          "compare_type": "<",
          "radius": 35,
          "value": 5
        }
      }
    }
  ]
}
